html_transfer_md/__init__.py
html_transfer_md/converter.py
html_transfer_md-0.1.0.dist-info/LICENSE
html_transfer_md-0.1.0.dist-info/METADATA
html_transfer_md-0.1.0.dist-info/WHEEL
html_transfer_md-0.1.0.dist-info/top_level.txt
html_transfer_md-0.1.0.dist-info/RECORD
